fsleyes/__init__.py
fsleyes/__main__.py
fsleyes/about.py
fsleyes/autodisplay.py
fsleyes/cliserver.py
fsleyes/colourmaps.py
fsleyes/filtermain.py
fsleyes/frame.py
fsleyes/icons.py
fsleyes/layouts.py
fsleyes/main.py
fsleyes/overlay.py
fsleyes/panel.py
fsleyes/parseargs.py
fsleyes/render.py
fsleyes/splash.py
fsleyes/state.py
fsleyes/strings.py
fsleyes/toolbar.py
fsleyes/tooltips.py
fsleyes/version.py
fsleyes/actions/__init__.py
fsleyes/actions/about.py
fsleyes/actions/applycommandline.py
fsleyes/actions/base.py
fsleyes/actions/browsexnat.py
fsleyes/actions/clearlayouts.py
fsleyes/actions/clearsettings.py
fsleyes/actions/copyoverlay.py
fsleyes/actions/diagnosticreport.py
fsleyes/actions/exportdataseries.py
fsleyes/actions/frameactions.py
fsleyes/actions/importdataseries.py
fsleyes/actions/loadatlas.py
fsleyes/actions/loadcolourmap.py
fsleyes/actions/loaddicom.py
fsleyes/actions/loadlayout.py
fsleyes/actions/loadoverlay.py
fsleyes/actions/loadoverlayfromdir.py
fsleyes/actions/loadplugin.py
fsleyes/actions/loadstandard.py
fsleyes/actions/loadvertexdata.py
fsleyes/actions/moviegif.py
fsleyes/actions/newimage.py
fsleyes/actions/notebook.py
fsleyes/actions/reloadoverlay.py
fsleyes/actions/removealloverlays.py
fsleyes/actions/removeoverlay.py
fsleyes/actions/runscript.py
fsleyes/actions/savelayout.py
fsleyes/actions/saveoverlay.py
fsleyes/actions/screenshot.py
fsleyes/actions/showcommandline.py
fsleyes/actions/togglecontrolpanel.py
fsleyes/actions/updatecheck.py
fsleyes/assets/colourmaps/README
fsleyes/assets/colourmaps/blue-lightblue.cmap
fsleyes/assets/colourmaps/blue.cmap
fsleyes/assets/colourmaps/cool.cmap
fsleyes/assets/colourmaps/copper.cmap
fsleyes/assets/colourmaps/cortical.cmap
fsleyes/assets/colourmaps/green.cmap
fsleyes/assets/colourmaps/greyscale.cmap
fsleyes/assets/colourmaps/hot.cmap
fsleyes/assets/colourmaps/hsv.cmap
fsleyes/assets/colourmaps/order.txt
fsleyes/assets/colourmaps/pink.cmap
fsleyes/assets/colourmaps/random.cmap
fsleyes-1.16.2.dist-info/licenses/LICENSE
fsleyes-1.16.2.dist-info/METADATA
fsleyes-1.16.2.dist-info/WHEEL
fsleyes-1.16.2.dist-info/entry_points.txt
fsleyes-1.16.2.dist-info/top_level.txt
fsleyes-1.16.2.dist-info/RECORD
