Metadata-Version: 2.4
Name: fsleyes
Version: 1.16.2
Summary: FSLeyes, the FSL image viewer
Author-email: Paul McCarthy <pauldmccarthy@gmail.com>
License: Apache License Version 2.0
Project-URL: Repository, https://git.fmrib.ox.ac.uk/fsl/fsleyes/fsleyes/
Project-URL: User documentation, https://open.win.ox.ac.uk/pages/fsl/fsleyes/fsleyes/userdoc/
Project-URL: API documentation, https://open.win.ox.ac.uk/pages/fsl/fsleyes/fsleyes/apidoc/
Classifier: Development Status :: 3 - Alpha
Classifier: Intended Audience :: Developers
Classifier: Intended Audience :: Science/Research
Classifier: License :: OSI Approved :: Apache Software License
Classifier: Programming Language :: Python :: 3.10
Classifier: Programming Language :: Python :: 3.11
Classifier: Programming Language :: Python :: 3.12
Classifier: Programming Language :: Python :: 3.13
Classifier: Topic :: Software Development :: Libraries :: Python Modules
Classifier: Topic :: Scientific/Engineering :: Visualization
Requires-Python: >=3.9
License-File: LICENSE
Requires-Dist: jinja2>=2
Requires-Dist: pillow>=3.2.0
Requires-Dist: pyopengl>=3.1.0
Requires-Dist: fsleyes-props>=1.12
Requires-Dist: fsleyes-widgets>=0.15
Requires-Dist: fslpy>=3.22
Requires-Dist: matplotlib>=3.5
Requires-Dist: nibabel>=2.3
Requires-Dist: numpy>=1.14
Requires-Dist: pyparsing>=2
Requires-Dist: scipy>=0.18
Requires-Dist: wxpython>=4
Provides-Extra: darwin
Requires-Dist: appnope==0.1.*; extra == "darwin"
Provides-Extra: extra
Requires-Dist: file-tree; extra == "extra"
Requires-Dist: file-tree-fsl; extra == "extra"
Requires-Dist: indexed_gzip>=0.7.0; extra == "extra"
Requires-Dist: ipykernel>=4.8; extra == "extra"
Requires-Dist: ipython>=5; extra == "extra"
Requires-Dist: jupyter_client>=5.3.1; extra == "extra"
Requires-Dist: nbclassic; extra == "extra"
Requires-Dist: pyzmq>=17.0; extra == "extra"
Requires-Dist: rtree>=0.8.3; extra == "extra"
Requires-Dist: tornado>=5.0; extra == "extra"
Requires-Dist: trimesh>=2.37.29; extra == "extra"
Requires-Dist: wxnatpy>=0.4.0; extra == "extra"
Requires-Dist: xnat>=0.3.3; extra == "extra"
Provides-Extra: doc
Requires-Dist: sphinx; extra == "doc"
Requires-Dist: sphinx-rtd-theme; extra == "doc"
Requires-Dist: sphinx-rtd-dark-mode; extra == "doc"
Provides-Extra: test
Requires-Dist: pytest; extra == "test"
Requires-Dist: coverage; extra == "test"
Requires-Dist: pytest-cov; extra == "test"
Requires-Dist: tomli; python_version < "3.11" and extra == "test"
Provides-Extra: style
Requires-Dist: pylint; extra == "style"
Requires-Dist: flake8; extra == "style"
Dynamic: license-file
